zepben/opendss/__init__.py
zepben/opendss/creators/__init__.py
zepben/opendss/creators/creator.py
zepben/opendss/creators/utils.py
zepben/opendss/creators/validators/__init__.py
zepben/opendss/creators/validators/validator.py
zepben/opendss/ewb/__init__.py
zepben/opendss/ewb/load/__init__.py
zepben/opendss/ewb/load/load_result.py
zepben/opendss/model/__init__.py
zepben/opendss/model/master.py
zepben/opendss/model/load/__init__.py
zepben/opendss/model/load/generator.py
zepben/opendss/model/load/growth_shape.py
zepben/opendss/model/load/growthshape.py
zepben/opendss/model/load/load.py
zepben/opendss/model/load/load_model.py
zepben/opendss/model/load/load_shape.py
zepben/opendss/model/load/power_conversion_element.py
zepben/opendss/model/metering/__init__.py
zepben/opendss/model/metering/energy_meter.py
zepben/opendss/model/metering/metering_model.py
zepben/opendss/model/metering/monitor.py
zepben/opendss/model/metering/target_element.py
zepben/opendss/model/network/__init__.py
zepben/opendss/model/network/bus.py
zepben/opendss/model/network/circuit.py
zepben/opendss/model/network/connection_point.py
zepben/opendss/model/network/dss_type.py
zepben/opendss/model/network/line.py
zepben/opendss/model/network/line_code.py
zepben/opendss/model/network/network_model.py
zepben/opendss/model/network/reg_control.py
zepben/opendss/model/network/transformer.py
zepben/opendss/reader/__init__.py
zepben/opendss/reader/opendss_reader.py
zepben/opendss/writer/__init__.py
zepben/opendss/writer/opendss_load_shape_writer.py
zepben/opendss/writer/opendss_writer.py
zepben.opendss-0.3.0.dist-info/LICENSE
zepben.opendss-0.3.0.dist-info/METADATA
zepben.opendss-0.3.0.dist-info/WHEEL
zepben.opendss-0.3.0.dist-info/top_level.txt
zepben.opendss-0.3.0.dist-info/RECORD
